enschema/__init__.py
enschema-0.1.5.dist-info/METADATA
enschema-0.1.5.dist-info/WHEEL
enschema-0.1.5.dist-info/RECORD
