Metadata-Version: 2.1
Name: enschema
Version: 0.1.5
Summary: 
Author: Martin Baláž
Author-email: martin.balaz@trojsten.sk
Requires-Python: >=3.10,<4.0
Classifier: Programming Language :: Python :: 3
Classifier: Programming Language :: Python :: 3.10
Classifier: Programming Language :: Python :: 3.11
Classifier: Programming Language :: Python :: 3.12
Requires-Dist: schema (>=0.7.0,<0.8.0)
